easy_icm_runner/__init__.py
easy_icm_runner/icm_runner.py
easy_icm_runner-2.3.0.dist-info/LICENSE
easy_icm_runner-2.3.0.dist-info/METADATA
easy_icm_runner-2.3.0.dist-info/WHEEL
easy_icm_runner-2.3.0.dist-info/top_level.txt
easy_icm_runner-2.3.0.dist-info/RECORD
