Metadata-Version: 2.1
Name: easy-icm-runner
Version: 2.3.0
Summary: A wrapper for IBM ICMs Scheduler API Calls'
Home-page: https://github.com/equinoxfitness/easy-icm-runner
Author: Bachir El Koussa
Author-email: bgkoussa@gmail.com
License: UNKNOWN
Platform: UNKNOWN
Classifier: Programming Language :: Python :: 3
Classifier: License :: OSI Approved :: MIT License
Classifier: Operating System :: OS Independent
Requires-Python: >=3.6
License-File: LICENSE
Requires-Dist: requests
